check_git_repos/__init__.py
check_git_repos-1.0.0.dist-info/entry_points.txt
check_git_repos-1.0.0.dist-info/WHEEL
check_git_repos-1.0.0.dist-info/METADATA
check_git_repos-1.0.0.dist-info/RECORD
