Metadata-Version: 2.1
Name: check-git-repos
Version: 1.0.0
Summary: A command line interface to check git repositories within a directory
Home-page: https://github.com/getyourguide/check-git-repos
Keywords: maintenance,tooling,git,cli
Author: Ben Ryves
Author-email: bryves@gmail.com
Requires-Python: >=3.7,<4.0
Classifier: Programming Language :: Python :: 3
Classifier: Programming Language :: Python :: 3.7
Classifier: Programming Language :: Python :: 3.8
Classifier: Programming Language :: Python :: 3.9
Requires-Dist: GitPython (>=3.1.24,<4.0.0)
Project-URL: Repository, https://github.com/getyourguide/check-git-repos
